jupyternetes_spawner/__init__.py
jupyternetes_spawner/_version.py
jupyternetes_spawner/spawner.py
jupyternetes_spawner/utils.py
jupyternetes_spawner/clients/__init__.py
jupyternetes_spawner/clients/clients/__init__.py
jupyternetes_spawner/clients/clients/kubernetes_client.py
jupyternetes_spawner/clients/clients/notebook_instance_client.py
jupyternetes_spawner/models/__init__.py
jupyternetes_spawner/models/models/__init__.py
jupyternetes_spawner/models/models/jupyter/__init__.py
jupyternetes_spawner/models/models/jupyter/notebook/__init__.py
jupyternetes_spawner/models/models/jupyter/notebook/instance/__init__.py
jupyternetes_spawner/models/models/jupyter/notebook/instance/v1_jupyter_notebook_instance.py
jupyternetes_spawner/models/models/jupyter/notebook/instance/v1_jupyter_notebook_instance_list.py
jupyternetes_spawner/models/models/jupyter/notebook/instance/v1_jupyter_notebook_instance_spec.py
jupyternetes_spawner/models/models/jupyter/notebook/instance/v1_jupyter_notebook_instance_spec_template.py
jupyternetes_spawner/models/models/jupyter/notebook/instance/v1_jupyter_notebook_instance_status.py
jupyternetes_spawner/models/models/jupyter/notebook/instance/v1_jupyter_notebook_instance_status_pod_resourcestate.py
jupyternetes_spawner/models/models/jupyter/notebook/instance/v1_jupyter_notebook_instance_status_resourcestate.py
jupyternetes_spawner/models/models/kubernetes/__init__.py
jupyternetes_spawner/models/models/kubernetes/v1_listmeta.py
jupyternetes_spawner/models/models/kubernetes/v1_managedfields_entry.py
jupyternetes_spawner/models/models/kubernetes/v1_objectmeta.py
jupyternetes_spawner/models/models/kubernetes/v1_owner_reference.py
jupyternetes_spawner/models/unit_test/__init__.py
jupyternetes_spawner/models/unit_test/mockers.py
jupyternetes_spawner/models/unit_test/test_notebook_instance.py
jupyternetes_spawner/unit_test/__init__.py
jupyternetes_spawner/unit_test/mockers.py
jupyternetes_spawner/unit_test/test_utils.py
jupyternetes_spawner-1.0.2.dist-info/METADATA
jupyternetes_spawner-1.0.2.dist-info/WHEEL
jupyternetes_spawner-1.0.2.dist-info/RECORD
